aws_http_auth/__init__.py
aws_http_auth/__main__.py
aws_http_auth/_version.py
aws_http_auth/credentials.py
aws_http_auth/http_auth.py
aws_http_auth/py.typed
aws_http_auth/signer.py
aws_http_auth-0.0.2.dist-info/METADATA
aws_http_auth-0.0.2.dist-info/WHEEL
aws_http_auth-0.0.2.dist-info/entry_points.txt
aws_http_auth-0.0.2.dist-info/licenses/LICENSE.txt
aws_http_auth-0.0.2.dist-info/RECORD
