Metadata-Version: 2.4
Name: aws-http-auth
Version: 0.0.2
Summary: Lightweight AWS SigV4 signing and HTTP authentication for httpx, requests, and raw HTTP clients—without the weight of boto3.
Project-URL: Documentation, https://github.com/FlavioAmurrioCS/aws-http-auth#readme
Project-URL: Issues, https://github.com/FlavioAmurrioCS/aws-http-auth/issues
Project-URL: Source, https://github.com/FlavioAmurrioCS/aws-http-auth
Author-email: Flavio Amurrio <25621374+FlavioAmurrioCS@users.noreply.github.com>
License-Expression: MIT
License-File: LICENSE.txt
Classifier: Development Status :: 4 - Beta
Classifier: Programming Language :: Python
Classifier: Programming Language :: Python :: 3.9
Classifier: Programming Language :: Python :: 3.10
Classifier: Programming Language :: Python :: 3.11
Classifier: Programming Language :: Python :: 3.12
Classifier: Programming Language :: Python :: 3.13
Classifier: Programming Language :: Python :: 3.14
Classifier: Programming Language :: Python :: Implementation :: CPython
Classifier: Programming Language :: Python :: Implementation :: PyPy
Requires-Python: >=3.9
Provides-Extra: tests
Requires-Dist: httpx; extra == 'tests'
Requires-Dist: pytest<8.4.0; extra == 'tests'
Requires-Dist: requests; extra == 'tests'
Requires-Dist: tomli; (python_version < '3.11') and extra == 'tests'
Provides-Extra: types
Requires-Dist: httpx; extra == 'types'
Requires-Dist: mypy; extra == 'types'
Requires-Dist: pyodide-http; extra == 'types'
Requires-Dist: pyrefly; extra == 'types'
Requires-Dist: pyright[nodejs]; extra == 'types'
Requires-Dist: pytest<8.4.0; extra == 'types'
Requires-Dist: requests; extra == 'types'
Requires-Dist: tomli; (python_version < '3.11') and extra == 'types'
Requires-Dist: ty; extra == 'types'
Requires-Dist: types-requests; extra == 'types'
Requires-Dist: typing-extensions; extra == 'types'
